[
    {
        "code": "82M1000NSP",
        "model": "Lenovo 14e Chr",
        "price": "608.21",
        "processor": "AMD 3000 Modelo de procesador 3015Ce Fabricante procesador AMD Frecuencia del",
        "ram": "4",
        "max_ram": "4",
        "storage": "32GB",
        "display_size": "14",
        "graphics": "AMD Radeon \nGraphics",
        "file_name": "82M1000NSP.txt"
    },
    {
        "code": "XJ58G",
        "model": "Dell Inspiron 15 3530R5-7530U16GB512GB SSD15.6\" FHD",
        "price": "554.33",
        "processor": "AMD Ryzen 7 Modelo de procesador Ryzen 7 7730U Fabricante procesador AMD",
        "ram": null,
        "max_ram": null,
        "storage": "512GB",
        "display_size": "15.6",
        "graphics": null,
        "file_name": "Dell Inspiron 15 3530R5-7530U16GB512GB SSD15.6_ FHD.txt"
    },
    {
        "code": "1D23K",
        "model": "Dell Inspiron 3030 Desktop 300W TPM i5-12400 8/512GB SSD",
        "price": "674.33",
        "processor": "Intel Core i5 Modelo del",
        "ram": null,
        "max_ram": null,
        "storage": "512GB",
        "display_size": null,
        "graphics": null,
        "file_name": "Dell Inspiron 3030 Desktop 300W TPM i5-12400 8.txt"
    },
    {
        "code": "GN4X0",
        "model": "Dell Latitude 9450 2-in-1 U7 165U 32GB/1TB SSD W11 P",
        "price": "2.54261",
        "processor": "Intel Core",
        "ram": null,
        "max_ram": null,
        "storage": "1TB",
        "display_size": "14",
        "graphics": null,
        "file_name": "Dell Latitude 9450 2-in-1 U7 165U 32GB.txt"
    },
    {
        "code": "FMDDY",
        "model": "Dell XPS 13 9350U7 258VEvo32GB1TB SSD13.4\" OLED Touch",
        "price": "2.30303",
        "processor": "Intel Core",
        "ram": null,
        "max_ram": null,
        "storage": "1TB",
        "display_size": "13.4",
        "graphics": null,
        "file_name": "Dell XPS 13 9350U7 258VEvo32GB1TB SSD13.4_ OLED Touch.txt"
    },
    {
        "code": "DTPF3",
        "model": "Dell XPS 14 9440U7 155H32GB1TB SSD14.5\" OLED Touch",
        "price": "2.62852",
        "processor": "Intel Core",
        "ram": "32",
        "max_ram": "32",
        "storage": "1TB",
        "display_size": "14.5",
        "graphics": null,
        "file_name": "Dell XPS 14 9440U7 155H32GB1TB SSD14.5_ OLED Touch.txt"
    },
    {
        "code": "NP960XGL-XG1ES",
        "model": "GALAXY BOOK4 ULTRA 16\", CORE ULTRA 7 155H 16GB 1TB",
        "price": "2.42546",
        "processor": "Intel® Core™ Ultra,",
        "ram": null,
        "max_ram": null,
        "storage": "1.000 GB",
        "display_size": "16",
        "graphics": null,
        "file_name": "GALAXY BOOK4 ULTRA 16_, CORE ULTRA 7 155H 16GB 1TB.txt"
    },
    {
        "code": "967X1ET",
        "model": "HP 250 G10 de 15,6 pulgadas",
        "price": "669.62",
        "processor": "Intel®[2], una rápida memoria y opciones de",
        "ram": null,
        "max_ram": null,
        "storage": "256 GB",
        "display_size": "15,6",
        "graphics": null,
        "file_name": "HP 250 G10 de 15,6 pulgadas.txt"
    },
    {
        "code": "623N5ET",
        "model": "HP Pro Torre 290 G9",
        "price": "693.82",
        "processor": "Intel®,",
        "ram": null,
        "max_ram": null,
        "storage": null,
        "display_size": null,
        "graphics": null,
        "file_name": "HP Pro Torre 290 G9.txt"
    },
    {
        "code": "82R400WTSP",
        "model": "Lenovo IdeaPad 1 15ALC7",
        "price": "604.33",
        "processor": "AMD Ryzen 5 Modelo de procesador Ryzen 5 5625U Fabricante procesador AMD Frecuencia del",
        "ram": "8",
        "max_ram": "8",
        "storage": "512GB",
        "display_size": "15.6",
        "graphics": "AMD Radeon \nGraphics",
        "file_name": "Lenovo IdeaPad 1 15ALC7.txt"
    },
    {
        "code": "21KE003VSP",
        "model": "Lenovo ThinkPad X1 2-in-1 Gen 9",
        "price": "2.54624",
        "processor": "Intel Core",
        "ram": null,
        "max_ram": null,
        "storage": "1.024 GB",
        "display_size": "14",
        "graphics": null,
        "file_name": "Lenovo ThinkPad X1 2-in-1 Gen 9.txt"
    },
    {
        "code": "16Z90R-E",
        "model": "LG gram 16Z90R/ Windows 11 Home/ i7/ 32GB/ 1TB SSD/ RTX",
        "price": "2.13000",
        "processor": "Intel® Core™ 13ª Generación, más potente y robusto que",
        "ram": null,
        "max_ram": null,
        "storage": "1TB",
        "display_size": "16",
        "graphics": null,
        "file_name": "LG gram 16Z90R.txt"
    },
    {
        "code": "17Z90R-E",
        "model": "LG gram 17Z90R 17\" Windows 11 Home i7 32GB 1TB SSD",
        "price": "2.20578",
        "processor": "Intel Core i7 Modelo de procesador i7-1360P Fabricante procesador Intel Frecuencia del",
        "ram": null,
        "max_ram": null,
        "storage": "1TB",
        "display_size": "17",
        "graphics": null,
        "file_name": "LG gram 17Z90R 17_ Windows 11 Home i7 32GB 1TB SSD.txt"
    },
    {
        "code": "ZKB-00012",
        "model": "Microsoft Surface Laptop 6 13.5 i7/32/1TB/Windows 11 Negro",
        "price": "2.52875",
        "processor": "Intel® Core Ultra serie H",
        "ram": null,
        "max_ram": null,
        "storage": "1.000 GB",
        "display_size": "13.5",
        "graphics": "Intel Arc \nGraphics",
        "file_name": "Microsoft Surface Laptop 6 13.5 i7.txt"
    },
    {
        "code": "Z1T-00012",
        "model": "Microsoft Surface Laptop Studio 2 i7/32/1T 2000 W11 Platino",
        "price": "3.78526",
        "processor": "Intel® de 13ª generación Intel Core i7-13800H•",
        "ram": null,
        "max_ram": null,
        "storage": "1.000 GB",
        "display_size": "4",
        "graphics": null,
        "file_name": "Microsoft Surface Laptop Studio 2 i7.txt"
    },
    {
        "code": "Y6B-00005",
        "model": "Microsoft Surface Pro 10 i7/32/512/W11 Platino",
        "price": "2.31145",
        "processor": "Intel Core",
        "ram": null,
        "max_ram": null,
        "storage": "512 GB",
        "display_size": "13",
        "graphics": null,
        "file_name": "Microsoft Surface Pro 10 i7.txt"
    },
    {
        "code": "MX2G3Y",
        "model": null,
        "price": "3.84900",
        "processor": "Apple M Modelo de procesador M4 Max Fabricante procesador Apple",
        "ram": null,
        "max_ram": null,
        "storage": "1.064 GB",
        "display_size": "14,2",
        "graphics": null,
        "file_name": "MX2G3Y.txt"
    },
    {
        "code": "PB63-B3011AH",
        "model": null,
        "price": "787.46",
        "processor": "Intel Core i3 Modelo del",
        "ram": null,
        "max_ram": null,
        "storage": null,
        "display_size": null,
        "graphics": "Intel \nUHD 730",
        "file_name": "PB63-B3011AH.txt"
    }
]